ncas_amof_netcdf_template/__init__.py
ncas_amof_netcdf_template/create_netcdf.py
ncas_amof_netcdf_template/file_info.py
ncas_amof_netcdf_template/remove_empty_variables.py
ncas_amof_netcdf_template/tsv2dict.py
ncas_amof_netcdf_template/util.py
ncas_amof_netcdf_template/values.py
ncas_amof_netcdf_template-2.5.2.dist-info/licenses/LICENSE
ncas_amof_netcdf_template-2.5.2.dist-info/METADATA
ncas_amof_netcdf_template-2.5.2.dist-info/WHEEL
ncas_amof_netcdf_template-2.5.2.dist-info/top_level.txt
ncas_amof_netcdf_template-2.5.2.dist-info/RECORD
