Metadata-Version: 2.4
Name: ncas_amof_netcdf_template
Version: 2.5.2
Summary: Package to create NCAS AMOF netCDF files.
Author-email: "Joshua M. Ralph-Hampton" <joshua.hampton@ncas.ac.uk>
License: MIT License
Project-URL: Homepage, https://github.com/joshua-hampton/ncas_amof_netcdf_template
Project-URL: Documentation, https://ncas-amof-netcdf-template.readthedocs.io/en/stable/
Keywords: NCAS,AMOF,netcdf,template,standard
Classifier: Development Status :: 5 - Production/Stable
Classifier: Environment :: Console
Classifier: Intended Audience :: Developers
Classifier: Intended Audience :: Science/Research
Classifier: License :: OSI Approved :: MIT License
Classifier: Natural Language :: English
Classifier: Operating System :: POSIX :: Linux
Classifier: Programming Language :: Python :: 3
Classifier: Programming Language :: Python :: 3.9
Classifier: Programming Language :: Python :: 3.10
Classifier: Programming Language :: Python :: 3.11
Classifier: Programming Language :: Python :: 3.12
Classifier: Programming Language :: Python :: 3.13
Classifier: Programming Language :: Python :: 3 :: Only
Classifier: Topic :: Scientific/Engineering
Classifier: Topic :: Software Development :: Libraries :: Python Modules
Requires-Python: <4,>=3.9
License-File: LICENSE
Requires-Dist: netcdf4
Requires-Dist: numpy
Requires-Dist: requests
Requires-Dist: pandas
Requires-Dist: pyyaml
Dynamic: license-file
